ingots/__init__.py
ingots/tests/__init__.py
ingots/tests/functionals/__init__.py
ingots/tests/units/__init__.py
ingots/tests/units/utils/__init__.py
ingots/tests/units/utils/test_packages_versions.py
ingots/utils/__init__.py
ingots/utils/packages_versions.py
scripts/__init__.py
scripts/create_package_version_file.py
ingots-0.1.0.dev1.dist-info/LICENSE
ingots-0.1.0.dev1.dist-info/METADATA
ingots-0.1.0.dev1.dist-info/WHEEL
ingots-0.1.0.dev1.dist-info/top_level.txt
ingots-0.1.0.dev1.dist-info/RECORD
